Metadata-Version: 1.1
Name: emase
Version: 0.10.5
Summary: EMASE: Expectation-Maximization algorithm for Allele Specific Expression
Home-page: https://github.com/churchill-lab/emase
Author: Kwangbom "KB" Choi
Author-email: kb.choi@jax.org
License: GPLv3
Keywords: emase
Platform: UNKNOWN
Classifier: Development Status :: 4 - Beta
Classifier: Intended Audience :: Developers
Classifier: License :: OSI Approved :: GNU General Public License v3 (GPLv3)
Classifier: Natural Language :: English
Classifier: Programming Language :: Python :: 2.6
Classifier: Programming Language :: Python :: 2.7
